covidcli/.pytest_cache/.gitignore
covidcli/.pytest_cache/CACHEDIR.TAG
covidcli/.pytest_cache/README.md
covidcli/.pytest_cache/v/cache/nodeids
covidcli/.pytest_cache/v/cache/stepwise
covidcli/__init__.py
covidcli/covidcli.py
covidcli/data/coronavirus_dataset.csv
covidcli-0.1.7.dist-info/entry_points.txt
covidcli-0.1.7.dist-info/LICENSE
covidcli-0.1.7.dist-info/WHEEL
covidcli-0.1.7.dist-info/METADATA
covidcli-0.1.7.dist-info/RECORD
