Metadata-Version: 2.1
Name: covidcli
Version: 0.1.7
Summary: Covidcli- A CLI For Tracking and Getting Info About Coronavirus Outbreak
Home-page: https://github.com/Jcharis/covidcli
License: MIT
Keywords: covidcli,covid,coronavirus,jcharistech,covid19,covid-cli,disease,WHO
Author: Jesse E.Agbe(JCharis)
Author-email: jcharistech@gmail.com
Requires-Python: >=3.3,<4.0
Classifier: License :: OSI Approved :: MIT License
Classifier: Operating System :: OS Independent
Classifier: Programming Language :: Python :: 3
Classifier: Programming Language :: Python :: 3.4
Classifier: Programming Language :: Python :: 3.5
Classifier: Programming Language :: Python :: 3.6
Classifier: Programming Language :: Python :: 3.7
Classifier: Programming Language :: Python :: 3.8
Requires-Dist: click (>=7.1.1,<8.0.0)
Requires-Dist: click-help-colors (>=0.8,<0.9)
Requires-Dist: pandas (==0.25.3)
Requires-Dist: pyfiglet (>=0.8.post1,<0.9)
Requires-Dist: tabulate (>=0.8.6,<0.9.0)
Project-URL: Repository, https://github.com/Jcharis/covidcli
